dockerfixtures/__init__.py
dockerfixtures/catalog.py
dockerfixtures/ci.py
dockerfixtures/container.py
dockerfixtures/image.py
dockerfixtures/placeholders.py
dockerfixtures/version.py
dockerfixtures-0.2.4.dist-info/COPYING
dockerfixtures-0.2.4.dist-info/METADATA
dockerfixtures-0.2.4.dist-info/WHEEL
dockerfixtures-0.2.4.dist-info/top_level.txt
dockerfixtures-0.2.4.dist-info/zip-safe
dockerfixtures-0.2.4.dist-info/RECORD
