Metadata-Version: 2.1
Name: dockerfixtures
Version: 0.2.4
Summary: Cointainers as Pytest fixtures made easy
Home-page: https://github.com/cans/python-docker-fixtures
Author: Nicolas CANIART
Author-email: nicolas@caniart.net
License: GPLv2
Project-URL: Code, https://github.com/cans/python-docker-fixtures
Project-URL: Issue-tracker, https://github.com/cans/python-docker-fixtures/issues
Keywords: docker,testing,fixtures
Platform: any
Classifier: Development Status :: 3 - Alpha
Classifier: Environment :: Console
Classifier: Intended Audience :: Developers
Classifier: License :: OSI Approved :: GNU General Public License v2 (GPLv2)
Classifier: Operating System :: OS Independent
Classifier: Programming Language :: Python
Classifier: Programming Language :: Python :: 3.7
Classifier: Programming Language :: Python :: 3.8
Classifier: Programming Language :: Python :: 3.9
Classifier: Programming Language :: Python :: 3.10
Classifier: Programming Language :: Python :: 3.11
Classifier: Topic :: Software Development :: Libraries :: Python Modules
Classifier: Typing :: Typed
Requires-Python: <3.12,>=3.7
License-File: COPYING
Requires-Dist: docker (~=4.1)
Provides-Extra: dev
Requires-Dist: build ; extra == 'dev'
Requires-Dist: coverage ; extra == 'dev'
Requires-Dist: kafka-python ; extra == 'dev'
Requires-Dist: pre-commit (<2.10.0) ; extra == 'dev'
Requires-Dist: pytest ; extra == 'dev'
Requires-Dist: pytest-cov ; extra == 'dev'
Requires-Dist: pytest-mock ; extra == 'dev'
Requires-Dist: Sphinx ; extra == 'dev'
Requires-Dist: twine ; extra == 'dev'
Requires-Dist: pdbpp ; (python_version < "3.9") and extra == 'dev'
Requires-Dist: ipdb ; (python_version >= "3.9") and extra == 'dev'
